pa/__init__.py
pa/alpha.py
pa/blur.py
pa/cmaps.py
pa/color_mixer.py
pa/compand.py
pa/contrast.py
pa/darken_group.py
pa/filters.py
pa/hist.py
pa/hue_sat_factor.py
pa/interp.py
pa/io.py
pa/lighten_group.py
pa/make_cmap.py
pa/sd_box.py
pa/sharpen.py
pa/sig.py
pa/space_convert.py
pa/strip.py
pa/unit_convert.py
pa/var_cmap_old.py
pa/adjust/__init__.py
pa/adjust/affine.py
pa/adjust/black_white.py
pa/adjust/blend.py
pa/adjust/res.py
pa/adjust/tile.py
pa/assets/photos.py
pa/assets/tex.py
pa/assets/photos/banana.jpg
pa/assets/photos/beetle.jpg
pa/assets/photos/bones.jpg
pa/assets/photos/bridge.jpg
pa/assets/photos/building.jpg
pa/assets/photos/buildings.jpg
pa/assets/photos/cow.jpg
pa/assets/photos/horses.jpg
pa/assets/photos/lighthouse.jpg
pa/assets/photos/magnolias.jpg
pa/assets/photos/mountains.jpg
pa/assets/photos/pelican.jpg
pa/assets/photos/scientist.jpg
pa/assets/photos/subway.jpg
pa/assets/photos/toronto.jpg
pa/assets/photos/woman_1.jpg
pa/assets/photos/woman_2.jpg
pa/assets/photos/woman_3.jpg
pa/assets/tex/gradient.png
pa/assets/tex/tie_dye.jpg
pa/cmaps/autumn.jpg
pa/cmaps/bone.jpg
pa/cmaps/cividis.jpg
pa/cmaps/cool.jpg
pa/cmaps/deep_green.jpg
pa/cmaps/hot.jpg
pa/cmaps/hsv.jpg
pa/cmaps/inferno.jpg
pa/cmaps/jet.jpg
pa/cmaps/magma.jpg
pa/cmaps/ocean.jpg
pa/cmaps/parula.jpg
pa/cmaps/pink.jpg
pa/cmaps/plasma.jpg
pa/cmaps/rainbow.jpg
pa/cmaps/spring.jpg
pa/cmaps/summer.jpg
pa/cmaps/turbo.jpg
pa/cmaps/twilight.jpg
pa/cmaps/twilight_shifted.jpg
pa/cmaps/viridis.jpg
pa/cmaps/winter.jpg
pa/comps/__init__.py
pa/comps/cmy.py
pa/comps/hsl.py
pa/comps/hsv.py
pa/comps/hue_sat.py
pa/comps/lab.py
pa/comps/luv.py
pa/comps/rgb.py
pa/comps/xyz.py
pa/comps/yuv.py
pa/dist/__init__.py
pa/dist/delta_e_1976.py
pa/dist/delta_e_1994.py
pa/dist/delta_e_2000.py
pa/lut/apply_gray_to_rgb_lut.py
pa/lut/apply_rgb_to_rgb_lut.py
pa/lut/id_rgb_to_rgb_lut.py
pa/lut/make_gray_to_rgb_lut.py
pa/misc/__init__.py
pa/misc/basic.py
pa/misc/const.py
pa/misc/im.py
pa/misc/interp.py
pa/misc/lerp.py
puzzleandy-45.dist-info/METADATA
puzzleandy-45.dist-info/WHEEL
puzzleandy-45.dist-info/licenses/LICENSE.txt
puzzleandy-45.dist-info/RECORD
