Metadata-Version: 2.4
Name: puzzleandy
Version: 45
License-Expression: MIT
License-File: LICENSE.txt
Classifier: Development Status :: 5 - Production/Stable
Classifier: License :: OSI Approved :: MIT License
Classifier: Topic :: Multimedia :: Graphics
Requires-Dist: coloraide
Requires-Dist: moderngl
Requires-Dist: numpy
Requires-Dist: opencv-python
Requires-Dist: scikit-image
Requires-Dist: wand
